magic/__init__.py
magic/magic.py
magic/libmagic/libmagic.dll
magic/libmagic/magic.mgc
python_magic_bin-0.4.13.dist-info/DESCRIPTION.rst
python_magic_bin-0.4.13.dist-info/METADATA
python_magic_bin-0.4.13.dist-info/RECORD
python_magic_bin-0.4.13.dist-info/WHEEL
python_magic_bin-0.4.13.dist-info/metadata.json
python_magic_bin-0.4.13.dist-info/top_level.txt
