Metadata-Version: 2.0
Name: python-magic-bin
Version: 0.4.13
Summary: File type identification using libmagic
Home-page: http://github.com/julian-r/python-magic
Author: Julian David Rath
Author-email: julian.rath@gmail.com
License: MIT
Keywords: mime magic file
Platform: UNKNOWN
Classifier: Intended Audience :: Developers
Classifier: License :: OSI Approved :: MIT License
Classifier: Programming Language :: Python
Classifier: Programming Language :: Python :: 2
Classifier: Programming Language :: Python :: 3
